src/diep/__init__.py
src/diep/cli.py
src/diep/config.py
diep-0.1.1.dist-info/LICENSE
diep-0.1.1.dist-info/METADATA
diep-0.1.1.dist-info/WHEEL
diep-0.1.1.dist-info/entry_points.txt
diep-0.1.1.dist-info/top_level.txt
diep-0.1.1.dist-info/RECORD
