Metadata-Version: 2.1
Name: diep
Version: 0.1.1
Summary: material representation via the direct integration of the external potential
Home-page: https://github.com/sheriftawfikabbas/diep
Author: Sherif Abdulkader Tawfik Abbas, Tri 
Author-email: sherif.tawfic@gmail.com
License: mit
Keywords: material science,graph neural networks,ai,machine learning
License-File: LICENSE
Requires-Dist: ase
Requires-Dist: dgl
Requires-Dist: pytorch_lightning
Requires-Dist: pymatgen
Requires-Dist: m3gnet
Requires-Dist: boto3
